{
  "Armor": {
    "count": 1872,
    "attributes": [
      "Charisma",
      "Clothing",
      "Conspicuousness",
      "DefenseSlash",
      "DefenseSmash",
      "DefenseStab",
      "FadeCoef",
      "IconId",
      "Id",
      "Material",
      "MaxQuality",
      "MaxStatus",
      "Model",
      "Name",
      "Noise",
      "PickpocketInPouch",
      "Price",
      "RPGBuffWeight",
      "SocialClassId",
      "StrReq",
      "UIInfo",
      "UIName",
      "UiSound",
      "Visibility",
      "VisibilityCoef",
      "WealthLevel",
      "Weight"
    ]
  },
  "MeleeWeapon": {
    "count": 561,
    "attributes": [
      "AgiReq",
      "Attack",
      "AttackModSlash",
      "AttackModSmash",
      "AttackModStab",
      "BrokenItemClassId",
      "Charisma",
      "Class",
      "Clothing",
      "Conspicuousness",
      "Defense",
      "DisplayInShop",
      "EntityScript",
      "FadeCoef",
      "IconId",
      "Id",
      "IsBreakable",
      "IsQuestItem",
      "LightSourcePriority",
      "Material",
      "MaxQuality",
      "MaxStatus",
      "Model",
      "Name",
      "PickpocketInPouch",
      "Price",
      "SharpeningAnimSuffix",
      "SocialClassId",
      "StrReq",
      "SubClass",
      "UIInfo",
      "UIName",
      "Visibility",
      "VisibilityCoef",
      "WealthLevel",
      "Weight"
    ]
  },
  "Horse": {
    "count": 503,
    "attributes": [
      "Charisma",
      "Clothing",
      "Conspicuousness",
      "DefenseSlash",
      "DefenseSmash",
      "DefenseStab",
      "FadeCoef",
      "IconId",
      "Id",
      "MaxQuality",
      "MaxStatus",
      "Model",
      "Name",
      "Noise",
      "Price",
      "RPGBuffWeight",
      "SocialClassId",
      "StrReq",
      "UIInfo",
      "UIName",
      "UiSound",
      "Visibility",
      "VisibilityCoef",
      "WealthLevel",
      "Weight"
    ]
  },
  "Hood": {
    "count": 126,
    "attributes": [
      "Charisma",
      "Clothing",
      "Conspicuousness",
      "DefenseSlash",
      "DefenseSmash",
      "DefenseStab",
      "FadeCoef",
      "IconId",
      "Id",
      "MaxQuality",
      "MaxStatus",
      "Name",
      "Noise",
      "Price",
      "SocialClassId",
      "StrReq",
      "UIInfo",
      "UIName",
      "UiSound",
      "Visibility",
      "VisibilityCoef",
      "WealthLevel",
      "Weight"
    ]
  },
  "Helmet": {
    "count": 108,
    "attributes": [
      "Charisma",
      "Clothing",
      "Conspicuousness",
      "DefenseSlash",
      "DefenseSmash",
      "DefenseStab",
      "EntityScript",
      "FadeCoef",
      "IconId",
      "Id",
      "MaxQuality",
      "MaxStatus",
      "Name",
      "Noise",
      "Price",
      "SocialClassId",
      "StrReq",
      "UIInfo",
      "UIName",
      "UiSound",
      "Visibility",
      "VisibilityCoef",
      "VisorTypeId",
      "WealthLevel",
      "Weight"
    ]
  },
  "ItemAlias": {
    "count": 41,
    "attributes": [
      "IconId",
      "Id",
      "IsQuestItem",
      "Name",
      "SourceItemId",
      "UIInfo",
      "UIName",
      "Weight"
    ]
  },
  "Die": {
    "count": 39,
    "attributes": [
      "FadeCoef",
      "IconId",
      "Id",
      "IsQuestItem",
      "Model",
      "Name",
      "PickpocketInPouch",
      "Price",
      "SideValues",
      "SideWeights",
      "UIInfo",
      "UIName",
      "VisibilityCoef",
      "Weight"
    ]
  },
  "MissileWeapon": {
    "count": 38,
    "attributes": [
      "AgiReq",
      "Charisma",
      "Class",
      "Conspicuousness",
      "Defense",
      "FadeCoef",
      "FireSoundMultiplicator",
      "HolsterModel",
      "IconId",
      "Id",
      "IsBreakable",
      "IsQuestItem",
      "LimbResistance",
      "MaxQuality",
      "MaxStatus",
      "Model",
      "Name",
      "OldFormula",
      "Power",
      "Price",
      "SocialClassId",
      "SoundSwitch",
      "StrReq",
      "UIInfo",
      "UIName",
      "Visibility",
      "VisibilityCoef",
      "WealthLevel",
      "Weight"
    ]
  },
  "DiceBadge": {
    "count": 31,
    "attributes": [
      "FadeCoef",
      "IconId",
      "Id",
      "Model",
      "Name",
      "PickpocketInPouch",
      "Price",
      "SubType",
      "Type",
      "UIInfo",
      "UIName",
      "VisibilityCoef",
      "Weight"
    ]
  },
  "QuickSlotContainer": {
    "count": 7,
    "attributes": [
      "Charisma",
      "Clothing",
      "Conspicuousness",
      "DefenseSlash",
      "DefenseSmash",
      "DefenseStab",
      "FadeCoef",
      "IconId",
      "Id",
      "MaxQuality",
      "MaxStatus",
      "Model",
      "Name",
      "Noise",
      "NumberOfQuickSlots",
      "PickpocketInPouch",
      "Price",
      "SocialClassId",
      "StrReq",
      "UIInfo",
      "UIName",
      "UiSound",
      "Visibility",
      "VisibilityCoef",
      "WealthLevel",
      "Weight"
    ]
  }
}